{
  "project_info": {
    "project_number": "892635274787",
    "project_id": "vibezapp1-4e647",
    "storage_bucket": "vibezapp1-4e647.firebasestorage.app"
  },
  "client": [
    {
      "client_info": {
        "mobilesdk_app_id": "1:892635274787:android:61fe64e5c276530c411b96",
        "android_client_info": {
          "package_name": "com.example.vibezapp10"
        }
      },
      "oauth_client": [],
      "api_key": [
        {
          "current_key": "AIzaSyAG3i7yEqthPH4WWs9ps_Wq8xxr-2udDO0"
        }
      ],
      "services": {
        "appinvite_service": {
          "other_platform_oauth_client": []
        }
      }
    }
  ],
  "configuration_version": "1"
}